parallelism/__init__.py
parallelism/api_reference.py
parallelism/config.py
parallelism/logger.py
parallelism/core/__init__.py
parallelism/core/raise_exception.py
parallelism/core/return_value.py
parallelism/core/scheduled_task.py
parallelism/core/scheduler_result.py
parallelism/core/task_scheduler.py
parallelism/core/exceptions/__init__.py
parallelism/core/exceptions/dependency_error.py
parallelism/core/exceptions/resource_error.py
parallelism/core/exceptions/worker_error.py
parallelism/core/executors/__init__.py
parallelism/core/executors/process_executor.py
parallelism/core/executors/thread_executor.py
parallelism/core/handlers/__init__.py
parallelism/core/handlers/dependency_handler.py
parallelism/core/handlers/function_handler.py
parallelism/core/handlers/parameters_handler.py
parallelism/core/handlers/resource_handler.py
parallelism/core/handlers/shared_memory_handler.py
parallelism/core/handlers/worker_handler.py
parallelism-0.1.4.dist-info/LICENSE
parallelism-0.1.4.dist-info/METADATA
parallelism-0.1.4.dist-info/WHEEL
parallelism-0.1.4.dist-info/top_level.txt
parallelism-0.1.4.dist-info/RECORD
