Metadata-Version: 2.1
Name: parallelism
Version: 0.1.4
Summary: Efficient parallel task scheduling and concurrency management
Author: Idan Hazan
License: MIT
Project-URL: homepage, https://github.com/idanhazan/parallelism
Project-URL: repository, https://github.com/idanhazan/parallelism
Project-URL: documentation, https://parallelism.readthedocs.io
Keywords: parallelism,parallel,concurrency,concurrent,scheduled,scheduling,scheduler,task,multitasking,process,multiprocessing,thread,multithreading
Classifier: Environment :: Console
Classifier: Intended Audience :: Developers
Classifier: License :: OSI Approved :: MIT License
Classifier: Operating System :: OS Independent
Classifier: Programming Language :: Python :: 3
Classifier: Programming Language :: Python :: 3.8
Classifier: Programming Language :: Python :: 3.9
Classifier: Programming Language :: Python :: 3.10
Classifier: Programming Language :: Python :: 3.11
Classifier: Topic :: Software Development :: Libraries :: Python Modules
Requires-Python: >=3.8
License-File: LICENSE
